ImgAlign/ImgAlign.py
ImgAlign/__init__.py
ImgAlign/raft/LICENSE.txt
ImgAlign/raft/__init__.py
ImgAlign/raft/corr.py
ImgAlign/raft/datasets.py
ImgAlign/raft/extractor.py
ImgAlign/raft/raft-things.pth
ImgAlign/raft/raft.py
ImgAlign/raft/update.py
ImgAlign/raft/utils/__init__.py
ImgAlign/raft/utils/augmentor.py
ImgAlign/raft/utils/flow_viz.py
ImgAlign/raft/utils/frame_utils.py
ImgAlign/raft/utils/utils.py
ImgAlign-4.1.dist-info/LICENSE
ImgAlign-4.1.dist-info/METADATA
ImgAlign-4.1.dist-info/WHEEL
ImgAlign-4.1.dist-info/entry_points.txt
ImgAlign-4.1.dist-info/top_level.txt
ImgAlign-4.1.dist-info/RECORD
