Metadata-Version: 2.1
Name: ImgAlign
Version: 4.1
License-File: LICENSE
Requires-Dist: mpl-interactions
Requires-Dist: matplotlib
Requires-Dist: numpy
Requires-Dist: opencv-contrib-python
Requires-Dist: scipy
Requires-Dist: scikit-learn
Requires-Dist: python-color-transfer
Requires-Dist: torch
